{"polls":[{"id":"1712211234001","type":"event","title":"봄맞이 야유회 및 라운딩","month":4,"date":"2026-04-24","course":"골프존카운티 송도","time":"07:00","fee":200000,"teams":8,"status":"closed","options":["라운딩+캠핑장 둘다참석","라운딩만 참석","캠핑장만 참석","둘다불참"],"votes":{"오유근":{"option":"라운딩+캠핑장 둘다참석","reason":"","timestamp":1774227600000},"신승우":{"option":"라운딩+캠핑장 둘다참석","reason":"","timestamp":1774231200000},"이광호":{"option":"라운딩+캠핑장 둘다참석","reason":"","timestamp":1774234800000},"이성구":{"option":"라운딩+캠핑장 둘다참석","reason":"","timestamp":1774238400000},"남기혁":{"option":"라운딩+캠핑장 둘다참석","reason":"","timestamp":1774242000000},"서경석":{"option":"둘다불참","reason":"","timestamp":1774246680000},"김은묵":{"option":"라운딩+캠핑장 둘다참석","reason":"","timestamp":1774249200000},"조성민":{"option":"라운딩+캠핑장 둘다참석","reason":"","timestamp":1774252800000},"김정택":{"option":"라운딩+캠핑장 둘다참석","reason":"","timestamp":1774256400000},"박지훈75":{"option":"라운딩+캠핑장 둘다참석","reason":"","timestamp":1774263600000},"박지훈79":{"option":"둘다불참","reason":"","timestamp":1774317600000},"심정수":{"option":"라운딩+캠핑장 둘다참석","reason":"","timestamp":1774310400000},"장원영":{"option":"라운딩+캠핑장 둘다참석","reason":"","timestamp":1774314000000},"최성윤":{"option":"라운딩+캠핑장 둘다참석","reason":"","timestamp":1774328400000},"홍동훈":{"option":"라운딩만 참석","reason":"","timestamp":1774350000000},"서지우":{"option":"둘다불참","reason":"","timestamp":1774400400000},"김대영":{"option":"라운딩만 참석","reason":"","timestamp":1774404000000},"이민형":{"option":"둘다불참","reason":"","timestamp":1774436400000},"배상필":{"option":"캠핑장만 참석","reason":"","timestamp":1774443600000},"김종천":{"option":"라운딩만 참석","reason":"","timestamp":1774486800000},"오성열":{"option":"캠핑장만 참석","reason":"","timestamp":1774490400000},"임형준":{"option":"둘다불참","reason":"","timestamp":1774497600000},"이재희":{"option":"캠핑장만 참석","reason":"","timestamp":1774504800000},"김두환":{"option":"둘다불참","reason":"","timestamp":1774573200000},"성종훈":{"option":"캠핑장만 참석","reason":"","timestamp":1774580400000},"문홍권":{"option":"캠핑장만 참석","reason":"","timestamp":1774587600000},"김용민":{"option":"둘다불참","reason":"","timestamp":1774594800000},"김정규":{"option":"둘다불참","reason":"","timestamp":1774659600000},"김길용":{"option":"캠핑장만 참석","reason":"","timestamp":1774666800000},"박다원":{"option":"둘다불참","reason":"","timestamp":1774673000000},"정일성":{"option":"둘다불참","reason":"","timestamp":1774746000000}},"comments":[{"name":"서경석","text":"비행이구먼","timestamp":1774246680000}]},{"id":"1712211234002","type":"regular","title":"5월 정기라운딩","month":5,"date":"2026-05-06","course":"클럽72 하늘코스","time":"13:00","fee":"250000","teams":"5","status":"closed","options":["참석","불참","대기"],"votes":{"김길용":{"option":"참석","reason":"","timestamp":1777704516522},"김대영":{"option":"참석","reason":"","timestamp":1775012400000},"김두환":{"option":"참석","reason":"","timestamp":1774872000000},"김용민":{"option":"참석","reason":"","timestamp":1775023200000},"김은묵":{"option":"참석","reason":"","timestamp":1774855800000},"김정택":{"option":"참석","reason":"","timestamp":1774861200000},"남기혁":{"option":"참석","reason":"","timestamp":1775019600000},"문홍권":{"option":"참석","reason":"","timestamp":1777704516522},"박지훈79":{"option":"참석","reason":"","timestamp":1774922400000},"박지훈75":{"option":"참석","reason":"","timestamp":1774864800000},"서경석":{"option":"참석","reason":"","timestamp":1774857600000},"양희모":{"option":"참석","reason":"","timestamp":1777704516522},"오성열":{"option":"참석","reason":"","timestamp":1775016000000},"오유근":{"option":"참석","reason":"","timestamp":1777704516522},"이광호":{"option":"참석","reason":"","timestamp":1774929600000},"이성구":{"option":"참석","reason":"","timestamp":1774926000000},"장원영":{"option":"참석","reason":"","timestamp":1777865623803},"정우전":{"option":"참석","reason":"","timestamp":1777704516522},"정일성":{"option":"참석","reason":"","timestamp":1774918800000},"김정규":{"option":"불참","reason":"","timestamp":1777704516522},"김종천":{"option":"불참","reason":"","timestamp":1777704516522},"박다원":{"option":"불참","reason":"","timestamp":1775001600000},"배상필":{"option":"불참","reason":"","timestamp":1777704516522},"서지우":{"option":"불참","reason":"","timestamp":1774854120000},"성종훈":{"option":"불참","reason":"","timestamp":1775091120000},"신승우":{"option":"불참","reason":"","timestamp":1777704516522},"이민형":{"option":"불참","reason":"","timestamp":1774879200000},"이재희":{"option":"불참","reason":"","timestamp":1775048400000},"이필선":{"option":"불참","reason":"","timestamp":1777704516522},"임형준":{"option":"불참","reason":"","timestamp":1775166000000},"조성민":{"option":"불참","reason":"","timestamp":1775112840000},"최성윤":{"option":"불참","reason":"","timestamp":1777704516522},"홍동훈":{"option":"불참","reason":"","timestamp":1777704516522},"오대성":{"option":"대기","reason":"","timestamp":1777704516522}},"comments":[{"name":"서지우","text":"태국출장....ㅠㅠ","timestamp":1774854120000},{"name":"성종훈","text":"군산에서 1박 2일로 잡혀있어요~~ㅠㅠ","timestamp":1775091120000},{"name":"조성민","text":"저도 다른일정하고 겹침","timestamp":1775112840000},{"name":"신승우","text":"▶일자 : 2026년 05월 06일  ▶코스 : 하늘IN 13:21, 하늘OUT 13:21, 하늘IN 13:28, 하늘OUT 13:28, 하늘IN 13:35,","timestamp":1777704796259},{"name":"신승우","text":"5팀마감합니다.","timestamp":1777704815097}]},{"id":"1777878040725","type":"regular","title":null,"month":6,"date":"2026-06-10","course":"클럽72 오션코스","time":"10:00","fee":"220000","teams":"7","options":["참석","불참","대기"],"multiSelect":false,"status":"closed","votes":{"신승우":{"option":"참석","reason":"","timestamp":1777878066874},"박지훈79":{"option":"참석","reason":"","timestamp":1777879157985},"김길용":{"option":"참석","reason":"","timestamp":1777879510358},"오대성":{"option":"참석","reason":"","timestamp":1777881270306},"김두환":{"option":"참석","reason":"","timestamp":1777890281586},"오성열":{"option":"참석","reason":"","timestamp":1777896461269},"정일성":{"option":"참석","reason":"","timestamp":1777900776916},"김용민":{"option":"불참","reason":"","timestamp":1777926815481},"박다원":{"option":"불참","reason":"","timestamp":1778603488237},"김은묵":{"option":"참석","reason":"","timestamp":1777944848665},"최성윤":{"option":"참석","reason":"","timestamp":1777944900272},"서경석":{"option":"참석","reason":"","timestamp":1777945353157},"오유근":{"option":"참석","reason":"","timestamp":1777947294169},"이광호":{"option":"참석","reason":"","timestamp":1777952780834},"임형준":{"option":"참석","reason":"","timestamp":1777954141488},"이재희":{"option":"불참","reason":"","timestamp":1777954269814},"서지우":{"option":"참석","reason":"","timestamp":1777954957612},"양희모":{"option":"참석","reason":"","timestamp":1777956952525},"박지훈75":{"option":"참석","reason":"","timestamp":1778035094935},"이민형":{"option":"불참","reason":"","timestamp":1778482740485},"홍동훈":{"option":"참석","reason":"","timestamp":1778488767624},"조성민":{"option":"참석","reason":"","timestamp":1778552885131},"배상필":{"option":"불참","reason":"","timestamp":1778552936552},"성종훈":{"option":"참석","reason":"","timestamp":1778557616189},"김정규":{"option":"불참","reason":"","timestamp":1778632935619},"장원영":{"option":"불참","reason":"","timestamp":1778651733135},"김정택":{"option":"참석","reason":"","timestamp":1778728932373},"김종천":{"option":"불참","reason":"","timestamp":1778811966169},"배현호":{"option":"참석","reason":"","timestamp":1778856832163},"정우전":{"option":"참석","reason":"","timestamp":1779600208099},"이필선":{"option":"참석","reason":"","timestamp":1779322950234},"심정수":{"option":"불참","reason":"","timestamp":1779410438073},"문홍권":{"option":"불참","reason":"","timestamp":1779412331897},"이성구":{"option":"참석","reason":"","timestamp":1779413384868},"김대영":{"option":"불참","reason":"","timestamp":1779434477421}},"comments":[{"name":"신승우","text":"6월달 정라는 1시대 하면 하늘 26마넌 10시대 하면 이벤트로 5만넌 할인 오션 오션=하늘 그린피 같음 이라고 해서 운영진단독결정으로 10시대로 진행하겠습니다.","timestamp":1777878076909},{"name":"배상필","text":"디스크 수술 후 라서 7월부터 참석할께요","timestamp":1778552982396},{"name":"신승우","text":"연단체명: gdr아카데미 시흥신천님 환영합니다! 챔피언의 역사가 깃든 오션코스에서 즐겁고 편안한 라운드 되시길 바랍니다.  ▶일자 : 06월10일(수) ▶코스 : 오션 OUT 10:23 OUT 10:30 OUT 10:37 OUT 10:44 IN 10:23 IN 10:30 IN 10:37  7팀 확정되었습니다.  * 1팀 4인 필수(3인내장시 4인 요금결제) * 레이크(IN)코스 배정시 20분전 카트탑승, 그외 코스는 10분전까지 카트탑승 부탁드립니다.  [골프비용]  - 그린피 인당 220,000원 - 카트피 팀당 100,000원 - 캐디피 팀당 160,000원","timestamp":1778632608757}]},{"id":"1779857663214","type":"event","title":"8월달 정기라운딩(태백 오투cc)","month":8,"date":"2026-08-07","course":"태백 오투CC","time":"13:00","fee":"160000","teams":"4","options":["참석","불참"],"multiSelect":false,"status":"active","votes":{"신승우":{"option":"참석","reason":"","timestamp":1779857831467},"박지훈75":{"option":"참석","reason":"","timestamp":1779858315094},"오유근":{"option":"참석","reason":"","timestamp":1779858397027},"서경석":{"option":"참석","reason":"","timestamp":1780281625146},"조성민":{"option":"참석","reason":"일단 무조건 신청","timestamp":1779858940835},"최성윤":{"option":"참석","reason":"","timestamp":1779859227042},"김은묵":{"option":"불참","reason":"상보참","timestamp":1779877131038},"김정규":{"option":"참석","reason":"","timestamp":1779865342323},"김길용":{"option":"참석","reason":"","timestamp":1779868336183},"서지우":{"option":"참석","reason":"","timestamp":1779875824379},"이광호":{"option":"참석","reason":"","timestamp":1779878139599},"배현호":{"option":"참석","reason":"","timestamp":1779889717150},"오성열":{"option":"참석","reason":"","timestamp":1779894651815},"정일성":{"option":"불참","reason":"","timestamp":1780280394232},"임형준":{"option":"불참","reason":"","timestamp":1780308481535},"김두환":{"option":"참석","reason":"","timestamp":1780559678371},"박다원":{"option":"참석","reason":"","timestamp":1781063051323},"정우전":{"option":"참석","reason":"","timestamp":1780989104362},"양희모":{"option":"참석","reason":"","timestamp":1781003465272},"김대영":{"option":"불참","reason":"","timestamp":1781146564459}},"comments":[{"name":"신승우","text":"🏌️ [송도마스터즈] 8월 정기 라운딩 계획 안내 및 참석 투표 회원 여러분 안녕하세요, 총무입니다. 연일 폭염인데 다들 건강 잘 챙기고 계시죠? 8월 정기 라운딩을 아래와 같이 계획 중이며, 인원 파악을 위해 참석 가능 여부 투표를 받습니다. 📅 일정: 8월 7일(금) ~ 8월 8일(토) / 1박 2일 📍 장소: 태백 오투(O2)리조트 CC 　🏔️ 해발 1,100m 고지대 · 여름 평균기온 22도 　→ 한낮에도 선선해 무더위 걱정 없이 라운딩하기 좋습니다. ⛳ 라운딩: 금·토 각 18홀 (총 2라운드) 🏨 숙박: 금요일 밤 1박 (리조트 내 객실) 💰 예상 비용 (1인 기준) · 그린피: 금요일 170,000원 + 토요일 210,000원 = 380,000원 　※ 단체요금은 12인(3팀) 이상 사전 예약 시 적용됩니다. · 숙박비: 객실타입에 따라 1박 230,000~310,000원 (객실 인원 분담) · 카트비·캐디피·식대 별도 (라운딩 후 정산) 🗳️ 참석 투표 아직 계획 단계입니다. 정확한 인원 파악을 위해 참석 가능하신 분은 투표 부탁드립니다. 1️⃣ 참석 가능합니다 2️⃣ 참석 어렵습니다 ⏰ 투표 마감: ○월 ○일(○) 인원이 확정되면 예약 진행 후 출발 시간·입금 계좌 등 세부사항을 별도 공지드리겠습니다. 문의는 총무에게 편하게 연락 주세요. 시원한 고지대에서 만나요! 😎","timestamp":1779858180931},{"name":"김길용","text":"일단참가~^^","timestamp":1779868318081},{"name":"김은묵","text":"난 상보참","timestamp":1779920243201}]},{"id":"1780279840882","type":"regular","title":null,"month":7,"date":"2026-07-01","course":"클럽72 하늘코스","time":"13:00","fee":"240000","teams":"7","options":["참석","불참","대기"],"multiSelect":false,"status":"active","votes":{"신승우":{"option":"참석","reason":"","timestamp":1780279870698},"이민형":{"option":"참석","reason":"","timestamp":1780280118515},"김은묵":{"option":"참석","reason":"","timestamp":1780280239831},"조성민":{"option":"참석","reason":"","timestamp":1780280360942},"박지훈79":{"option":"참석","reason":"","timestamp":1781063643295},"서지우":{"option":"참석","reason":"","timestamp":1780280700886},"이광호":{"option":"참석","reason":"","timestamp":1780281515921},"서경석":{"option":"참석","reason":"","timestamp":1780281602211},"김정규":{"option":"불참","reason":"","timestamp":1780282739992},"임형준":{"option":"참석","reason":"","timestamp":1780308460333},"오성열":{"option":"참석","reason":"","timestamp":1780310924017},"김길용":{"option":"참석","reason":"","timestamp":1780398551411},"김대영":{"option":"참석","reason":"","timestamp":1780537585199},"배상필":{"option":"참석","reason":"","timestamp":1780545860444},"최성윤":{"option":"참석","reason":"","timestamp":1780546306610},"박지훈75":{"option":"참석","reason":"","timestamp":1780547198359},"김정택":{"option":"참석","reason":"","timestamp":1780547269394},"남기혁":{"option":"참석","reason":"","timestamp":1780548200388},"김종천":{"option":"불참","reason":"","timestamp":1780548870435},"홍동훈":{"option":"참석","reason":"","timestamp":1780559464843},"정일성":{"option":"참석","reason":"","timestamp":1780559577621},"이재희":{"option":"불참","reason":"","timestamp":1780573495363},"김두환":{"option":"참석","reason":"","timestamp":1780658555573},"박다원":{"option":"불참","reason":"","timestamp":1781063028037},"양희모":{"option":"참석","reason":"","timestamp":1781003291388},"장원영":{"option":"참석","reason":"","timestamp":1781073347839},"배현호":{"option":"참석","reason":"","timestamp":1781147567261}},"comments":[{"name":"신승우","text":"그린피는 미확정입니다. 23~24만원 날씨에 따라서","timestamp":1780279906233},{"name":"신승우","text":"[원더클럽] 클럽72 하늘+연습장 연단체07월 배정안내 예약확정  gdr아카데미 시흥신천님 환영합니다! 하늘과 바다가 맞닿은 절경의 하늘코스에서 즐겁고 편안한 라운드 되시길 바랍니다.  ▶일자 : 07월01일(수) ▶코스 : 하늘 OUT 13:21 OUT 13:28 OUT 13:35 OUT 13:42 IN 13:21 IN 13:28 IN 13:35  7팀 확정되었습니다.    * 1팀 4인 필수(3인내장시 4인 요금결제)  [골프비용]  - 그린피 인당 240,000원 - 카트피 팀당 100,000원 - 캐디피 팀당 160,000원 - 뷔페 이용료 15,000원(라운드 전 이용가능)    ＊연단체 조편성: 라운드일 기준 7일전까지 등록   원더클럽 홈페이지/어플 > MY페이지>연단체/임시단체 선택   (회원명+연락처+성별 등록 후 저장) ＊라운드 전일 17시까지 조편성 수정 가능, 이후 변경불가합니다. ＊팀수 변경 및 취소시 라운드일 제외 8일전까지 연락주시기 바랍니다.   (라운드일 제외 8일전 17시이후 취소시 위약금 부과)    * 하늘코스 주소 : 인천시 중구 공항동로 135번길 267  ■ 하늘코스, 골프연습장 특별 이벤트 상품 * 자세한 내용은 원더클럽 홈페이지 공지사항 참조   ※ 문의) 클럽72예약실  1599-0072 (내선2번)","timestamp":1780545773470}]}]}